README.txt
setup.py
apigateway/__init__.py
apigateway/admin.py
apigateway/models.py
apigateway/tests.py
apigateway/urls.py
apigateway/views.py
apigateway/migrations/__init__.py
django_api_gateway.egg-info/PKG-INFO
django_api_gateway.egg-info/SOURCES.txt
django_api_gateway.egg-info/dependency_links.txt
django_api_gateway.egg-info/top_level.txt