Metadata-Version: 1.0
Name: django-api-gateway
Version: 0.0.6
Summary: apigateway for django
Home-page: https://github.com/sarar04/djangoapigateway
Author: sarar04
Author-email: sarar04@163.com
License: MIT License
Keywords: django,apigateway,dataproxy
Platform: unix like
